<Properties StartupConfiguration="{859E218F-EC3D-43E5-957B-EE04BD5E2772}|Default">
  <MonoDevelop.Ide.Workbench ActiveDocument="Startup.cs">
    <Files>
      <File FileName="Pages/Shared/_Layout.cshtml" Line="73" Column="19" />
      <File FileName="Areas/Identity/Pages/_ViewStart.cshtml" Line="4" Column="1" />
      <File FileName="Pages/Shared/_LoginPartial.cshtml" Line="1" Column="1" />
      <File FileName="Pages/_ViewImports.cshtml" Line="1" Column="1" />
      <File FileName="Pages/_ViewStart.cshtml" Line="1" Column="1" />
      <File FileName="Pages/Error.cshtml" Line="1" Column="1" />
      <File FileName="Pages/Error.cshtml.cs" Line="1" Column="1" />
      <File FileName="Pages/Index.cshtml" Line="1" Column="1" />
      <File FileName="Pages/Index.cshtml.cs" Line="1" Column="1" />
      <File FileName="Pages/Privacy.cshtml" Line="2" Column="20" />
      <File FileName="Startup.cs" Line="46" Column="1" />
    </Files>
    <Pads>
      <Pad Id="ProjectPad">
        <State name="__root__">
          <Node name="entrepreneur_tc_auth" expanded="True">
            <Node name="entrepreneur_tc_auth" expanded="True">
              <Node name="Pages" expanded="True" />
              <Node name="Startup.cs" selected="True" />
            </Node>
          </Node>
        </State>
      </Pad>
    </Pads>
  </MonoDevelop.Ide.Workbench>
  <MonoDevelop.Ide.ItemProperties.entrepreneur__tc__auth PreferredExecutionTarget="MonoDevelop.Default" />
  <MonoDevelop.Ide.DebuggingService.PinnedWatches />
  <MonoDevelop.Ide.Workspace ActiveConfiguration="Debug" />
  <MonoDevelop.Ide.DebuggingService.Breakpoints>
    <BreakpointStore />
  </MonoDevelop.Ide.DebuggingService.Breakpoints>
  <MultiItemStartupConfigurations />
</Properties>